README
setup.cfg
setup.py
pymrgeo/__init__.py
pymrgeo/code_generator.py
pymrgeo/constants.py
pymrgeo/instance.py
pymrgeo/java_gateway.py
pymrgeo/mapopgenerator.py
pymrgeo/mrgeo.py
pymrgeo/rastermapop.py
pymrgeo/vectormapop.py
pymrgeo.egg-info/PKG-INFO
pymrgeo.egg-info/SOURCES.txt
pymrgeo.egg-info/dependency_links.txt
pymrgeo.egg-info/top_level.txt