Metadata-Version: 1.1
Name: pymrgeo
Version: 1.0.1
Summary: MrGeo (pronounced "Mister Geo") is an open source geospatial toolkit designed to provide raster-based geospatial processing capabilities performed at scale. MrGeo enables global geospatial big data image processing and analytics.
Home-page: https://github.com/ngageoint/mrgeo
Author: Tim Tisler and Dave Johnson
Author-email: tim.tisler@digitalglobe.com and dave.johnson@digitalglobe.com
License: Apache 2.0
Keywords: geospatial toolkit hadoop apache spark raster-based
Platform: UNKNOWN
Classifier: Development Status :: 5 - Production/Stable
Classifier: Intended Audience :: Science/Research
Classifier: Intended Audience :: Developers
Classifier: Topic :: Software Development :: Libraries :: Python Modules
Classifier: License :: OSI Approved :: Apache Software License
Classifier: Programming Language :: Python :: 2.7
Classifier: Programming Language :: Python :: 3
Classifier: Programming Language :: Python :: 3.3
Classifier: Programming Language :: Python :: 3.4
Classifier: Programming Language :: Python :: 3.5
